shadowai/__init__.py
shadowai/ai.py
shadowai/network.py
shadowai/vectorizer.py
shadowai_turkish-0.1.0.dist-info/METADATA
shadowai_turkish-0.1.0.dist-info/WHEEL
shadowai_turkish-0.1.0.dist-info/top_level.txt
shadowai_turkish-0.1.0.dist-info/RECORD
