Metadata-Version: 2.4
Name: ShadowAI-Turkish
Version: 0.1.0
Summary: Kendi kendine öğrenen, sana ait yapay zeka
Author: Eymen Efe
Requires-Python: >=3.8
